gitnu/__init__.py
gitnu/__main__.py
gitnu/cache.py
gitnu/data_structure.py
gitnu/git.py
gitnu/log.py
gitnu/read.py
gitnu/shell.py
gitnu/strings.py
gitnu/tests.py
gitnu/write.py
gitnu-0.1.0.dist-info/LICENSE
gitnu-0.1.0.dist-info/METADATA
gitnu-0.1.0.dist-info/WHEEL
gitnu-0.1.0.dist-info/entry_points.txt
gitnu-0.1.0.dist-info/top_level.txt
gitnu-0.1.0.dist-info/RECORD
