Metadata-Version: 2.1
Name: gitnu
Version: 0.1.0
Summary: Enumerate git status
Author: Khang
Author-email: brew4k@gmail.com
License: UNKNOWN
Project-URL: Source, https://github.com/nguyenvukhang/gitnu
Keywords: git,cli,python3
Platform: UNKNOWN
Classifier: Intended Audience :: Developers
Classifier: Programming Language :: Python :: 3
Classifier: Operating System :: Unix
Classifier: Operating System :: MacOS :: MacOS X
License-File: LICENSE
